dual_autodiff_x/__init__.py
dual_autodiff_x/base.cpython-312-darwin.so
dual_autodiff_x/dual.cpython-312-darwin.so
dual_autodiff_x/functions.cpython-312-darwin.so
dual_autodiff_x/version.cpython-312-darwin.so
rsr45_dual_autodiff_x-0.1.17.dist-info/METADATA
rsr45_dual_autodiff_x-0.1.17.dist-info/WHEEL
rsr45_dual_autodiff_x-0.1.17.dist-info/top_level.txt
rsr45_dual_autodiff_x-0.1.17.dist-info/RECORD
