Metadata-Version: 2.1
Name: rsr45-dual-autodiff-x
Version: 0.1.17
Summary: A package for dual number-based automatic differentiation
License: MIT
Project-URL: Homepage, https://pypi.org/project/rsr45-dual-autodiff-x/
Requires-Python: >=3.6
